ew/__init__.py
ew/core.py
ew/errors.py
ew/fields.py
ew/forms.py
ew/jinja2_ew.py
ew/middleware.py
ew/render.py
ew/resource.py
ew/select.py
ew/utils.py
ew/validators.py
ew/widget.py
ew/templates/__init__.py
ew/templates/jinja2/__init__.py
ew/templates/jinja2/_ew_lib.html
ew/templates/jinja2/checkbox.html
ew/templates/jinja2/checkbox_set.html
ew/templates/jinja2/field_set.html
ew/templates/jinja2/google_analytics.html
ew/templates/jinja2/repeated_field.html
ew/templates/jinja2/row_field.html
ew/templates/jinja2/select_field.html
ew/templates/jinja2/simple_form.html
ew/templates/jinja2/table_field.html
ew/tests/__init__.py
ew/tests/helpers.py
ew/tests/test_fields.py
ew/tests/test_resource.py
ew/tests/test_utils.py
ew/tests/test_widget.py
ew/tests/templates/__init__.py
ew/tests/templates/simple.html
easywidgets-0.4.3.dist-info/METADATA
easywidgets-0.4.3.dist-info/WHEEL
easywidgets-0.4.3.dist-info/entry_points.txt
easywidgets-0.4.3.dist-info/top_level.txt
easywidgets-0.4.3.dist-info/RECORD
