Metadata-Version: 2.4
Name: EasyWidgets
Version: 0.4.3
Summary: A minimalistic approach to HTML generation and validation with TurboGears
Home-page: https://sourceforge.net/p/easywidgets/code/
Author: Rick Copeland
Author-email: rick446@usa.net
License: MIT
Project-URL: Documentation, http://easywidgets.pythonisito.com
Project-URL: Source Code, https://sourceforge.net/p/easywidgets/code/
Keywords: TurboGears FormEncode TurboGears2
Classifier: Development Status :: 3 - Alpha
Classifier: Environment :: Web Environment
Classifier: Framework :: TurboGears
Classifier: Framework :: TurboGears :: Widgets
Classifier: Intended Audience :: Developers
Classifier: License :: OSI Approved :: MIT License
Classifier: Natural Language :: English
Classifier: Operating System :: OS Independent
Classifier: Programming Language :: Python
Classifier: Programming Language :: Python :: 3.10
Classifier: Programming Language :: Python :: 3.11
Classifier: Programming Language :: Python :: 3.12
Classifier: Programming Language :: Python :: 3.13
Classifier: Programming Language :: Python :: 3.14
Requires-Python: >=3.10
Requires-Dist: python-dateutil
Requires-Dist: formencode
Requires-Dist: markupsafe
Requires-Dist: paste
Requires-Dist: webob
Dynamic: author
Dynamic: author-email
Dynamic: classifier
Dynamic: description
Dynamic: home-page
Dynamic: keywords
Dynamic: license
Dynamic: project-url
Dynamic: requires-dist
Dynamic: requires-python
Dynamic: summary
